LICENSE
MANIFEST.in
setup.py
sortedfile.py
sortedfile.egg-info/PKG-INFO
sortedfile.egg-info/SOURCES.txt
sortedfile.egg-info/dependency_links.txt
sortedfile.egg-info/top_level.txt