Metadata-Version: 1.0
Name: sortedfile
Version: 0.3
Summary: Logarithmic search for sorted text files.
Home-page: http://github.com/dw/sortedfile/
Author: David Wilson
Author-email: dw@botanicus.net
License: Apache 2
Platform: UNKNOWN
